{
  "source_file_path_relative_to_docusaurus_root": "versioned_docs/version-2.7.2/release-2.5-tracking.md",
  "source_file_content_hash": "6d4911cb628ee1601d10c733ab0532f30505682261a27d0b7e9eb1d1a3922737",
  "segments": [
    {
      "segment_id": "58cfcc64",
      "source_content": "---\ntitle: Chaos Mesh v2.5.0 Tracking\n---",
      "source_content_hash": "d2dc5d84e575fc572adb22c7a808c45d0c8760058a3c4b28b7592c1ebe3176d8",
      "node_type": "yaml",
      "translatable": false,
      "translations": {
        "ja": "@@untranslatable_placeholder_58cfcc64"
      }
    },
    {
      "segment_id": "f85bbfb4",
      "source_content": "## Links",
      "source_content_hash": "7621e916cb6e57b50af80e3a9a11646e43c81f3c516a44eb8b0a0f4c2557dd02",
      "node_type": "heading",
      "translatable": true,
      "translations": {
        "ja": "## リンク"
      }
    },
    {
      "segment_id": "57e757df",
      "source_content": "- [Chaos Mesh release cycle](release-cycle.md)",
      "source_content_hash": "9689fc907a14ee8736c606134d04648dc234b3b38d8a1bfdf01d906f64c6425c",
      "node_type": "list",
      "translatable": true,
      "translations": {
        "ja": "- [Chaos Mesh リリースサイクル](release-cycle.md)"
      }
    },
    {
      "segment_id": "d912d376",
      "source_content": "## Tracking Docs",
      "source_content_hash": "8fddb3e5edde07baff16d0e9dea9928bb8303915098f185aa064f1659a37bb94",
      "node_type": "heading",
      "translatable": true,
      "translations": {
        "ja": "## 追跡ドキュメント"
      }
    },
    {
      "segment_id": "be33979e",
      "source_content": "- [Release 2.5 Milestone](https://github.com/chaos-mesh/chaos-mesh/milestone/12)\n- [Docs Milestone](https://github.com/chaos-mesh/website/milestone/4)",
      "source_content_hash": "6b579b48924b991d75c7b70128d4f441cc4e4c0c6fa59063b935a78774d09207",
      "node_type": "list",
      "translatable": true,
      "translations": {
        "ja": "- [リリース 2.5 マイルストーン](https://github.com/chaos-mesh/chaos-mesh/milestone/12)\n- [ドキュメントマイルストーン](https://github.com/chaos-mesh/website/milestone/4)"
      }
    },
    {
      "segment_id": "70153c6e",
      "source_content": "## Release manager",
      "source_content_hash": "2b5f347ac500a8155023f75c2886a4b41fe846d7bc1b016b6efc45fb0559fe75",
      "node_type": "heading",
      "translatable": true,
      "translations": {
        "ja": "## リリースマネージャー"
      }
    },
    {
      "segment_id": "4ddf6ae7",
      "source_content": "- [STRRL](https://github.com/STRRL)",
      "source_content_hash": "7ab15d32765ecbb446e18a11166b799c9a2e43e6cd2b0a674653e1aa336bdff9",
      "node_type": "list",
      "translatable": true,
      "translations": {
        "ja": "- [STRRL](https://github.com/STRRL)"
      }
    },
    {
      "segment_id": "d350c018",
      "source_content": "## Summary",
      "source_content_hash": "30ac03ff33731529441be8fbe52a3bd0d4c5ec830e806d54692168ebb7f98ada",
      "node_type": "heading",
      "translatable": true,
      "translations": {
        "ja": "## 概要"
      }
    },
    {
      "segment_id": "3dd19309",
      "source_content": "| When | Week | As Developer | As Release Manager | Notes |\n| :-: | :-: | :-: | :-: | :-: |\n| Monday 26 Sept 2022 | Week 1 | Normal Dev | Normal Dev |  |\n| Monday 31 Oct 2022 | Week 6 | Code Freeze; Fix bugs | Code Freeze |  |\n| Monday 7 Nov 2022 | Week 7 | Code Freeze; Fix bugs | Cut new branch release 2.5 | Cleanup the CHANGELOG on master; Cherry pick bugfixes |\n| Monday 14 Nov 2022 | Week 8 | Fix bugs | Release Minor Version |  |",
      "source_content_hash": "2032b70dde59eef4c79bae15c7ae70aa7398e214acc27729fc4e163b3c55b045",
      "node_type": "table",
      "translatable": false,
      "translations": {
        "ja": "@@untranslatable_placeholder_3dd19309"
      }
    }
  ],
  "target_i18n_subpath": "docusaurus-plugin-content-docs/version-2.7.2/release-2.5-tracking.md",
  "last_updated_timestamp": "2025-06-05T17:50:36.662802+00:00",
  "schema_version": "1.0",
  "translated_versions": {
    "ja": "6d4911cb628ee1601d10c733ab0532f30505682261a27d0b7e9eb1d1a3922737"
  }
}